pycasbin_firebase_adapter/__init__.py
pycasbin_firebase_adapter/__version__.py
pycasbin_firebase_adapter/adapter.py
pycasbin_firebase_adapter-0.0.1.data/data/README.md
pycasbin_firebase_adapter-0.0.1.dist-info/LICENSE
pycasbin_firebase_adapter-0.0.1.dist-info/METADATA
pycasbin_firebase_adapter-0.0.1.dist-info/WHEEL
pycasbin_firebase_adapter-0.0.1.dist-info/top_level.txt
pycasbin_firebase_adapter-0.0.1.dist-info/RECORD
