Metadata-Version: 2.1
Name: pycasbin-firebase-adapter
Version: 0.0.1
Summary: Fibase Adapter for PyCasbin
Home-page: https://github.com/devrushi41/pycasbin-firebase-adapter
Author: DevRushi
Author-email: devrushi41@gmail.com
License: Apache 2.0
Keywords: casbin,firebase,casbin-adapter,rbac,access control,abac,acl,permission
Platform: UNKNOWN
Classifier: Programming Language :: Python :: 3.5
Classifier: Programming Language :: Python :: 3.6
Classifier: Programming Language :: Python :: 3.7
Classifier: Programming Language :: Python :: 3.8
Classifier: Programming Language :: Python :: 3.9
Classifier: License :: OSI Approved :: Apache Software License
Classifier: Operating System :: OS Independent
Requires-Python: >=3.3
Requires-Dist: casbin (>=0.8.1)
Requires-Dist: firebase-admin (>=5.0.0)
